{
  "info": {
    "_postman_id": "20112008-841c-4f8f-abd9-d4297ced497f",
    "name": "Team Task Board API",
    "description": "REST API for users, projects, and tasks (SQLite + Bun).",
    "schema": "https://schema.getpostman.com/json/collection/v2.1.0/collection.json",
    "_exporter_id": "40101962"
  },
  "item": [
    {
      "name": "Meta",
      "item": [
        {
          "name": "API Root",
          "request": {
            "method": "GET",
            "header": [],
            "url": {
              "raw": "{{base_url}}/",
              "host": [
                "{{base_url}}"
              ],
              "path": [
                ""
              ]
            },
            "description": "Returns service info and available resources."
          },
          "response": []
        },
        {
          "name": "Health Check",
          "request": {
            "method": "GET",
            "header": [],
            "url": {
              "raw": "{{base_url}}/health",
              "host": [
                "{{base_url}}"
              ],
              "path": [
                "health"
              ]
            },
            "description": "Returns { status: ok } if server is running."
          },
          "response": []
        }
      ]
    },
    {
      "name": "Users",
      "item": [
        {
          "name": "List Users",
          "request": {
            "method": "GET",
            "header": [],
            "url": {
              "raw": "{{base_url}}/users?page=1&page_size=20",
              "host": [
                "{{base_url}}"
              ],
              "path": [
                "users"
              ],
              "query": [
                {
                  "key": "page",
                  "value": "1"
                },
                {
                  "key": "page_size",
                  "value": "20"
                },
                {
                  "key": "search",
                  "value": "",
                  "disabled": true
                }
              ]
            },
            "description": "List all users with optional search and pagination."
          },
          "response": []
        },
        {
          "name": "Search Users",
          "request": {
            "method": "GET",
            "header": [],
            "url": {
              "raw": "{{base_url}}/users?search=Alex",
              "host": [
                "{{base_url}}"
              ],
              "path": [
                "users"
              ],
              "query": [
                {
                  "key": "search",
                  "value": "Alex"
                }
              ]
            },
            "description": "Search users by name or email."
          },
          "response": []
        },
        {
          "name": "Create User",
          "request": {
            "method": "POST",
            "header": [
              {
                "key": "Content-Type",
                "value": "application/json"
              }
            ],
            "body": {
              "mode": "raw",
              "raw": "{\n  \"email\": \"new@example.com\",\n  \"name\": \"New User\"\n}"
            },
            "url": {
              "raw": "{{base_url}}/users",
              "host": [
                "{{base_url}}"
              ],
              "path": [
                "users"
              ]
            },
            "description": "Create a new user. Email must be unique."
          },
          "response": []
        },
        {
          "name": "Get User by ID",
          "request": {
            "method": "GET",
            "header": [],
            "url": {
              "raw": "{{base_url}}/users/1",
              "host": [
                "{{base_url}}"
              ],
              "path": [
                "users",
                "1"
              ]
            },
            "description": "Get a single user by their ID."
          },
          "response": []
        },
        {
          "name": "Update User",
          "request": {
            "method": "PATCH",
            "header": [
              {
                "key": "Content-Type",
                "value": "application/json"
              }
            ],
            "body": {
              "mode": "raw",
              "raw": "{\n  \"name\": \"Updated Name\"\n}"
            },
            "url": {
              "raw": "{{base_url}}/users/1",
              "host": [
                "{{base_url}}"
              ],
              "path": [
                "users",
                "1"
              ]
            },
            "description": "Update a user's name or email (partial update)."
          },
          "response": []
        },
        {
          "name": "Delete User",
          "request": {
            "method": "DELETE",
            "header": [],
            "url": {
              "raw": "{{base_url}}/users/1",
              "host": [
                "{{base_url}}"
              ],
              "path": [
                "users",
                "1"
              ]
            },
            "description": "Delete a user by ID. Returns 200 with a confirmation message."
          },
          "response": []
        },
        {
          "name": "Get User - 404",
          "request": {
            "method": "GET",
            "header": [],
            "url": {
              "raw": "{{base_url}}/users/9999",
              "host": [
                "{{base_url}}"
              ],
              "path": [
                "users",
                "9999"
              ]
            },
            "description": "Example of a not found response."
          },
          "response": []
        },
        {
          "name": "Create User - Duplicate Email 409",
          "request": {
            "method": "POST",
            "header": [
              {
                "key": "Content-Type",
                "value": "application/json"
              }
            ],
            "body": {
              "mode": "raw",
              "raw": "{\n  \"email\": \"new@example.com\",\n  \"name\": \"Dupe\"\n}"
            },
            "url": {
              "raw": "{{base_url}}/users",
              "host": [
                "{{base_url}}"
              ],
              "path": [
                "users"
              ]
            },
            "description": "Example of a duplicate email conflict response."
          },
          "response": []
        }
      ]
    },
    {
      "name": "Projects",
      "item": [
        {
          "name": "List Projects",
          "request": {
            "method": "GET",
            "header": [],
            "url": {
              "raw": "{{base_url}}/projects?page=1&page_size=20",
              "host": [
                "{{base_url}}"
              ],
              "path": [
                "projects"
              ],
              "query": [
                {
                  "key": "page",
                  "value": "1"
                },
                {
                  "key": "page_size",
                  "value": "20"
                },
                {
                  "key": "owner_id",
                  "value": "",
                  "disabled": true
                },
                {
                  "key": "status",
                  "value": "",
                  "disabled": true
                }
              ]
            },
            "description": "List all projects with optional filtering by owner or status."
          },
          "response": []
        },
        {
          "name": "List Active Projects",
          "request": {
            "method": "GET",
            "header": [],
            "url": {
              "raw": "{{base_url}}/projects?status=active",
              "host": [
                "{{base_url}}"
              ],
              "path": [
                "projects"
              ],
              "query": [
                {
                  "key": "status",
                  "value": "active"
                }
              ]
            },
            "description": "Filter projects by status=active."
          },
          "response": []
        },
        {
          "name": "Create Project",
          "request": {
            "method": "POST",
            "header": [
              {
                "key": "Content-Type",
                "value": "application/json"
              }
            ],
            "body": {
              "mode": "raw",
              "raw": "{\n  \"owner_id\": 1,\n  \"name\": \"New Project\",\n  \"description\": \"A sample project\",\n  \"status\": \"active\"\n}"
            },
            "url": {
              "raw": "{{base_url}}/projects",
              "host": [
                "{{base_url}}"
              ],
              "path": [
                "projects"
              ]
            },
            "description": "Create a new project. owner_id must reference an existing user."
          },
          "response": []
        },
        {
          "name": "Get Project by ID",
          "request": {
            "method": "GET",
            "header": [],
            "url": {
              "raw": "{{base_url}}/projects/1",
              "host": [
                "{{base_url}}"
              ],
              "path": [
                "projects",
                "1"
              ]
            },
            "description": "Get a single project by its ID."
          },
          "response": []
        },
        {
          "name": "Update Project",
          "request": {
            "method": "PATCH",
            "header": [
              {
                "key": "Content-Type",
                "value": "application/json"
              }
            ],
            "body": {
              "mode": "raw",
              "raw": "{\n  \"status\": \"archived\"\n}"
            },
            "url": {
              "raw": "{{base_url}}/projects/1",
              "host": [
                "{{base_url}}"
              ],
              "path": [
                "projects",
                "1"
              ]
            },
            "description": "Update a project's name, description, or status."
          },
          "response": []
        },
        {
          "name": "Delete Project",
          "request": {
            "method": "DELETE",
            "header": [],
            "url": {
              "raw": "{{base_url}}/projects/1",
              "host": [
                "{{base_url}}"
              ],
              "path": [
                "projects",
                "1"
              ]
            },
            "description": "Delete a project by ID. Also deletes all tasks in that project (cascade)."
          },
          "response": []
        },
        {
          "name": "Create Project - Bad Owner 422",
          "request": {
            "method": "POST",
            "header": [
              {
                "key": "Content-Type",
                "value": "application/json"
              }
            ],
            "body": {
              "mode": "raw",
              "raw": "{\n  \"owner_id\": 9999,\n  \"name\": \"Bad Project\"\n}"
            },
            "url": {
              "raw": "{{base_url}}/projects",
              "host": [
                "{{base_url}}"
              ],
              "path": [
                "projects"
              ]
            },
            "description": "Example of invalid owner_id returning 422."
          },
          "response": []
        }
      ]
    },
    {
      "name": "Tasks",
      "item": [
        {
          "name": "List Tasks",
          "request": {
            "method": "GET",
            "header": [],
            "url": {
              "raw": "{{base_url}}/tasks?page=1&page_size=20",
              "host": [
                "{{base_url}}"
              ],
              "path": [
                "tasks"
              ],
              "query": [
                {
                  "key": "page",
                  "value": "1"
                },
                {
                  "key": "page_size",
                  "value": "20"
                },
                {
                  "key": "project_id",
                  "value": "",
                  "disabled": true
                },
                {
                  "key": "assignee_id",
                  "value": "",
                  "disabled": true
                },
                {
                  "key": "status",
                  "value": "",
                  "disabled": true
                },
                {
                  "key": "min_priority",
                  "value": "",
                  "disabled": true
                }
              ]
            },
            "description": "List all tasks with optional filtering."
          },
          "response": []
        },
        {
          "name": "List Tasks by Status",
          "request": {
            "method": "GET",
            "header": [],
            "url": {
              "raw": "{{base_url}}/tasks?status=todo",
              "host": [
                "{{base_url}}"
              ],
              "path": [
                "tasks"
              ],
              "query": [
                {
                  "key": "status",
                  "value": "todo"
                }
              ]
            },
            "description": "Filter tasks by status. Valid values: todo, doing, done."
          },
          "response": []
        },
        {
          "name": "List Tasks by Min Priority",
          "request": {
            "method": "GET",
            "header": [],
            "url": {
              "raw": "{{base_url}}/tasks?min_priority=2",
              "host": [
                "{{base_url}}"
              ],
              "path": [
                "tasks"
              ],
              "query": [
                {
                  "key": "min_priority",
                  "value": "2"
                }
              ]
            },
            "description": "Filter tasks with priority >= value. Range: 1–3."
          },
          "response": []
        },
        {
          "name": "Create Task",
          "request": {
            "method": "POST",
            "header": [
              {
                "key": "Content-Type",
                "value": "application/json"
              }
            ],
            "body": {
              "mode": "raw",
              "raw": "{\n  \"project_id\": 1,\n  \"assignee_id\": 2,\n  \"title\": \"New Task\",\n  \"description\": \"Task details here\",\n  \"status\": \"todo\",\n  \"priority\": 1,\n  \"due_date\": \"2026-05-01\"\n}"
            },
            "url": {
              "raw": "{{base_url}}/tasks",
              "host": [
                "{{base_url}}"
              ],
              "path": [
                "tasks"
              ]
            },
            "description": "Create a new task. project_id is required; assignee_id is optional."
          },
          "response": []
        },
        {
          "name": "Get Task by ID",
          "request": {
            "method": "GET",
            "header": [],
            "url": {
              "raw": "{{base_url}}/tasks/1",
              "host": [
                "{{base_url}}"
              ],
              "path": [
                "tasks",
                "1"
              ]
            },
            "description": "Get a single task by its ID."
          },
          "response": []
        },
        {
          "name": "Update Task",
          "request": {
            "method": "PATCH",
            "header": [
              {
                "key": "Content-Type",
                "value": "application/json"
              }
            ],
            "body": {
              "mode": "raw",
              "raw": "{\n  \"status\": \"done\"\n}"
            },
            "url": {
              "raw": "{{base_url}}/tasks/1",
              "host": [
                "{{base_url}}"
              ],
              "path": [
                "tasks",
                "1"
              ]
            },
            "description": "Update any task field. All fields are optional."
          },
          "response": []
        },
        {
          "name": "Delete Task",
          "request": {
            "method": "DELETE",
            "header": [],
            "url": {
              "raw": "{{base_url}}/tasks/3",
              "host": [
                "{{base_url}}"
              ],
              "path": [
                "tasks",
                "3"
              ]
            },
            "description": "Delete a task by ID. Returns 204 with no content."
          },
          "response": []
        },
        {
          "name": "Delete Task - 404",
          "request": {
            "method": "DELETE",
            "header": [],
            "url": {
              "raw": "{{base_url}}/tasks/3",
              "host": [
                "{{base_url}}"
              ],
              "path": [
                "tasks",
                "3"
              ]
            },
            "description": "Example of deleting an already-deleted task."
          },
          "response": []
        },
        {
          "name": "Create Task - Bad Project 422",
          "request": {
            "method": "POST",
            "header": [
              {
                "key": "Content-Type",
                "value": "application/json"
              }
            ],
            "body": {
              "mode": "raw",
              "raw": "{\n  \"project_id\": 9999,\n  \"title\": \"Ghost Task\"\n}"
            },
            "url": {
              "raw": "{{base_url}}/tasks",
              "host": [
                "{{base_url}}"
              ],
              "path": [
                "tasks"
              ]
            },
            "description": "Example of invalid project_id returning 422."
          },
          "response": []
        }
      ]
    }
  ],
  "variable": [
    {
      "key": "base_url",
      "value": "http://localhost:3000",
      "type": "string"
    }
  ]
}